{
  "version": "1.0",
  "timestamp": "2026-06-10T20:02:16.618Z",
  "phase": "01",
  "phase_name": "Persistent Sessions & Storage Foundation",
  "phase_dir": ".planning/phases/01-persistent-sessions-storage-foundation",
  "plan": 0,
  "task": 0,
  "total_tasks": 0,
  "status": "paused",
  "completed_tasks": [],
  "remaining_tasks": [],
  "blockers": [],
  "human_actions_pending": [],
  "decisions": [
    {"decision": "Use JWT generated/verified on ESP32", "rationale": "Avoids NVS write wear on sessions", "phase": "1"},
    {"decision": "Waive 5-device limit", "rationale": "100% NVS wear mitigation for sessions", "phase": "1"},
    {"decision": "No session expiration", "rationale": "Maximum convenience for Koi pond owners", "phase": "1"},
    {"decision": "IP Binding", "rationale": "Mitigate HTTP sniffing risks on local Wi-Fi", "phase": "1"},
    {"decision": "Client-side only logout", "rationale": "Accepted risk to avoid NVS writes", "phase": "1"}
  ],
  "uncommitted_files": [],
  "next_action": "Run /gsd-plan-phase 1 to begin planning",
  "context_notes": "Phase 1 context gathered via gsd-discuss-phase. User chose to use stateless JWTs with IP binding and no expiration."
}
